{
  "classification": "stage_d3a3_reconstructed_energy_by_frame", 
  "frames": [
    {
      "Gc": 0.0027, 
      "bulk_energy_from_SDV12": 0.0, 
      "fracture_energy_gradient_term": 0.0, 
      "fracture_energy_local_term": 0.0, 
      "frame_tag": "F0_ingested", 
      "lc": 0.015, 
      "maximum_detJ": null, 
      "method": "target_Q4_2x2_bulk_SDV12_plus_AT2_fracture_energy", 
      "minimum_detJ": null, 
      "missing_phase_node_values": 25600, 
      "missing_sdv12_values": 0, 
      "missing_sdv13_values": 0, 
      "non_positive_detJ_count": 0, 
      "phase_l2": null, 
      "phase_max": null, 
      "phase_min": null, 
      "phase_range": null, 
      "thickness": 1.0, 
      "total_fracture_energy": 0.0, 
      "total_reconstructed_internal_energy": 0.0, 
      "undamaged_bulk_energy_from_SDV13": 0.0
    }, 
    {
      "Gc": 0.0027, 
      "bulk_energy_from_SDV12": 0.0, 
      "fracture_energy_gradient_term": 0.0, 
      "fracture_energy_local_term": 0.0, 
      "frame_tag": "F1_equilibrated", 
      "lc": 0.015, 
      "maximum_detJ": null, 
      "method": "target_Q4_2x2_bulk_SDV12_plus_AT2_fracture_energy", 
      "minimum_detJ": null, 
      "missing_phase_node_values": 25600, 
      "missing_sdv12_values": 0, 
      "missing_sdv13_values": 0, 
      "non_positive_detJ_count": 0, 
      "phase_l2": null, 
      "phase_max": null, 
      "phase_min": null, 
      "phase_range": null, 
      "thickness": 1.0, 
      "total_fracture_energy": 0.0, 
      "total_reconstructed_internal_energy": 0.0, 
      "undamaged_bulk_energy_from_SDV13": 0.0
    }, 
    {
      "Gc": 0.0027, 
      "bulk_energy_from_SDV12": 0.0, 
      "fracture_energy_gradient_term": 0.0, 
      "fracture_energy_local_term": 0.0, 
      "frame_tag": "F2_release_first", 
      "lc": 0.015, 
      "maximum_detJ": null, 
      "method": "target_Q4_2x2_bulk_SDV12_plus_AT2_fracture_energy", 
      "minimum_detJ": null, 
      "missing_phase_node_values": 25600, 
      "missing_sdv12_values": 0, 
      "missing_sdv13_values": 0, 
      "non_positive_detJ_count": 0, 
      "phase_l2": null, 
      "phase_max": null, 
      "phase_min": null, 
      "phase_range": null, 
      "thickness": 1.0, 
      "total_fracture_energy": 0.0, 
      "total_reconstructed_internal_energy": 0.0, 
      "undamaged_bulk_energy_from_SDV13": 0.0
    }, 
    {
      "Gc": 0.0027, 
      "bulk_energy_from_SDV12": 0.0, 
      "fracture_energy_gradient_term": 0.0, 
      "fracture_energy_local_term": 0.0, 
      "frame_tag": "F3_release_last", 
      "lc": 0.015, 
      "maximum_detJ": null, 
      "method": "target_Q4_2x2_bulk_SDV12_plus_AT2_fracture_energy", 
      "minimum_detJ": null, 
      "missing_phase_node_values": 25600, 
      "missing_sdv12_values": 0, 
      "missing_sdv13_values": 0, 
      "non_positive_detJ_count": 0, 
      "phase_l2": null, 
      "phase_max": null, 
      "phase_min": null, 
      "phase_range": null, 
      "thickness": 1.0, 
      "total_fracture_energy": 0.0, 
      "total_reconstructed_internal_energy": 0.0, 
      "undamaged_bulk_energy_from_SDV13": 0.0
    }
  ], 
  "method": "target_Q4_2x2_bulk_SDV12_plus_AT2_fracture_energy"
}
